monisys/__init__.py
monisys/monicli.py
monisys/Managers/Arguments.py
monisys/Managers/Systeminfo.py
monisys/Managers/__init__.py
monisys/Managers/manager.py
monisys/Managers/systeminfocli.py
monisys-0.3.dist-info/METADATA
monisys-0.3.dist-info/WHEEL
monisys-0.3.dist-info/entry_points.txt
monisys-0.3.dist-info/top_level.txt
monisys-0.3.dist-info/RECORD
