Metadata-Version: 2.1
Name: monisys
Version: 0.3
Summary: Monisys with tool we can able to moniter entire os
Home-page: https://github.com/prasaanth2k/monisys
Author: Prasaanth Sakthivel
Author-email: prasaanth@gmail.com
License: MIT
Classifier: License :: OSI Approved :: MIT License
Classifier: Programming Language :: Python :: 3.9
Requires-Python: >=3.6
Requires-Dist: rich
